qiskit_extension/__init__.py
qiskit_extension/ket.py
qiskit_extension/latex_drawer.py
qiskit_extension/quantum_circuit2.py
qiskit_extension/state_vector2.py
qiskit_extension/config/__init__.py
qiskit_extension/config/config.ini
qiskit_extension/utils/__init__.py
qiskit_extension/utils/find_nth_substring.py
qiskit_extension/utils/float_gcd.py
qiskit_extension/utils/inverse_tensor.py
qiskit_extension/utils/np_extension.py
QiskitExtension-0.1.4.dist-info/LICENSE.md
QiskitExtension-0.1.4.dist-info/METADATA
QiskitExtension-0.1.4.dist-info/WHEEL
QiskitExtension-0.1.4.dist-info/top_level.txt
QiskitExtension-0.1.4.dist-info/RECORD
