Metadata-Version: 2.1
Name: QiskitExtension
Version: 0.1.4
Summary: A Qiskit visualize extension
Home-page: https://github.com/Slope86/QiskitExtension
Author: HSIEH, LI-YU
Author-email: cjh9027@smail.nchu.edu.tw
License: MIT
Classifier: Development Status :: 3 - Alpha
Classifier: Programming Language :: Python :: 3.10
Classifier: Programming Language :: Python :: 3.11
Classifier: License :: OSI Approved :: MIT License
Classifier: Operating System :: OS Independent
Requires-Python: >=3.10
License-File: LICENSE.md
Requires-Dist: qiskit[visualization] ==1.0.0
Requires-Dist: qiskit-aer ==0.13.3
